{
  "project_info": {
    "project_number": "601943563754",
    "project_id": "wellyfe-d650c",
    "storage_bucket": "wellyfe-d650c.appspot.com"
  },
  "client": [
    {
      "client_info": {
        "mobilesdk_app_id": "1:601943563754:android:8fc2645524a08cf7116693",
        "android_client_info": {
          "package_name": "com.ericcheah.wellyfe_app"
        }
      },
      "oauth_client": [
        {
          "client_id": "601943563754-8ubbol2dt561nvtc13ol5u3pmu3c0ght.apps.googleusercontent.com",
          "client_type": 3
        }
      ],
      "api_key": [
        {
          "current_key": "AIzaSyDAa_fEKZAw-SiBohy-ptj5MAw3xUaLnvc"
        }
      ],
      "services": {
        "appinvite_service": {
          "other_platform_oauth_client": [
            {
              "client_id": "601943563754-8ubbol2dt561nvtc13ol5u3pmu3c0ght.apps.googleusercontent.com",
              "client_type": 3
            }
          ]
        }
      }
    }
  ],
  "configuration_version": "1"
}